sunspec_ardexa.py
sunspec_ardexa-1.3.10.dist-info/DESCRIPTION.rst
sunspec_ardexa-1.3.10.dist-info/METADATA
sunspec_ardexa-1.3.10.dist-info/RECORD
sunspec_ardexa-1.3.10.dist-info/WHEEL
sunspec_ardexa-1.3.10.dist-info/entry_points.txt
sunspec_ardexa-1.3.10.dist-info/metadata.json
sunspec_ardexa-1.3.10.dist-info/top_level.txt
