Metadata-Version: 2.0
Name: sunspec-ardexa
Version: 1.3.10
Summary: Collect from Sunspec Inverters and send the data to your cloud using Ardexa
Home-page: https://github.com/ardexa/sunspec-inverters
Author: Ardexa Pty Limited
Author-email: support@ardexa.com
License: UNKNOWN
Project-URL: Source, https://github.com/ardexa/sunspec-inverters/
Project-URL: Bug Reports, https://github.com/ardexa/sunspec-inverters/issues
Keywords: sunspec solar inverter ardexa
Platform: UNKNOWN
Classifier: License :: OSI Approved :: MIT License
Classifier: Programming Language :: Python :: 2
Classifier: Programming Language :: Python :: 2.7
Classifier: Programming Language :: Python :: 3
Classifier: Programming Language :: Python :: 3.4
Classifier: Programming Language :: Python :: 3.5
Classifier: Programming Language :: Python :: 3.6
Requires-Python: >=2.7
Requires-Dist: Click
Requires-Dist: ardexaplugin
Requires-Dist: future
